tpg/__init__.py
tpg/config.py
tpg/extract_unsupported_operators.py
tpg/generate.py
tpg/log.py
tpg/tpg.py
tpg/yaml_parser.py
tpg/plugin_templates/IPluginV2DynamicExt.cpp
tpg/plugin_templates/IPluginV2DynamicExt.h
tpg/plugin_templates/IPluginV2IOExt.cpp
tpg/plugin_templates/IPluginV2IOExt.h
tpg/plugin_templates/license.template
tpg/plugin_templates/makefile
tpg/plugin_templates/supported_operator_trt84.txt
trtpg-1.3.0.dist-info/LICENSE.md
trtpg-1.3.0.dist-info/METADATA
trtpg-1.3.0.dist-info/WHEEL
trtpg-1.3.0.dist-info/entry_points.txt
trtpg-1.3.0.dist-info/top_level.txt
trtpg-1.3.0.dist-info/RECORD
