Metadata-Version: 2.1
Name: trtpg
Version: 1.3.0
Summary: Generate TensorRT plugin in fly
Home-page: https://github.com/NVIDIA-AI-IOT/tensorrt_plugin_generator
Author-email: cntse@nvidia.com
License: UNKNOWN
Keywords: tensorrt plugin generator
Platform: linux
Classifier: Intended Audience :: Developers
Classifier: Programming Language :: Python :: 3
License-File: LICENSE.md
Requires-Dist: pyyaml
Requires-Dist: numpy
Requires-Dist: onnx
